nwae/broadcaster/AggregateServer.py
nwae/broadcaster/Authenticate.py
nwae/broadcaster/BroadcastHandler.py
nwae/broadcaster/BroadcastServer.py
nwae/broadcaster/BroadcastThread.py
nwae/broadcaster/CleanupThread.py
nwae/broadcaster/ClientWsHandler.py
nwae/broadcaster/ExamplePushPull.py
nwae/broadcaster/Feed.py
nwae/broadcaster/FeedQueue.py
nwae/broadcaster/SampleClient.py
nwae/broadcaster/SessionFeedThread.py
nwae/broadcaster/SubscriberList.py
nwae/broadcaster/config/Config.py
nwae/broadcaster/subscriber/SubscriberSharedSecret.py
nwae.broadcaster-1.2.1.dist-info/METADATA
nwae.broadcaster-1.2.1.dist-info/WHEEL
nwae.broadcaster-1.2.1.dist-info/top_level.txt
nwae.broadcaster-1.2.1.dist-info/RECORD
