Metadata-Version: 2.1
Name: nwae.broadcaster
Version: 1.2.1
Summary: Push/Pull (Rest POST/GET) & Broadcast (Web Socket Streaming) Any Feed
Home-page: UNKNOWN
Author: nwae
Author-email: mapktah@ya.ru
License: UNKNOWN
Platform: UNKNOWN
Requires-Dist: nwae.utils
Requires-Dist: Flask
Requires-Dist: gevent
Requires-Dist: gevent-websocket
